{
    "homepage": "https://developer.android.com/studio/command-line/aapt2",
    "description": "Android Asset Packaging Tool 2.",
    "license": "Apache-2.0",
    "version": "4.2.0-alpha04-6589975",
    "url": "https://dl.google.com/dl/android/maven2/com/android/tools/build/aapt2/4.2.0-alpha04-6589975/aapt2-4.2.0-alpha04-6589975-windows.jar#/dl.7z",
    "hash": "234d6c4a735b5d576ed4ac3cb17abd6a82b426884e00fe5a8aa8011e6a322d11",
    "bin": "aapt2.exe",
    "checkver": {
        "url": "https://mvnrepository.com/artifact/com.android.tools.build/aapt2",
        "regex": "(?sm)align=\"center\">Version.*?<a href=\"aapt2/(([\\d.]+)(-[\\d\\w]+)?-([\\d]+))\""
    },
    "autoupdate": {
        "url": "https://dl.google.com/dl/android/maven2/com/android/tools/build/aapt2/$version/aapt2-$version-windows.jar#/dl.7z"
    }
}
