{
    "homepage": "https://github.com/baulk/baulk",
    "description": "Minimal Package Manager for Windows",
    "version": "2.1.0",
    "license": "MIT",
    "architecture": {
        "64bit": {
            "url": "https://github.com/baulk/baulk/releases/download/2.1.0/Baulk-2.1.0-win-x64.zip",
            "hash": "7b19dfd409e18595bd9e90b74ad7678d9a0260bf529f70bba753ab90c0edfa44",
            "extract_dir": "Baulk-2.1.0-win-x64"
        },
        "32bit": {
            "url": "https://github.com/baulk/baulk/releases/download/2.1.0/Baulk-2.1.0-win-x86.zip",
            "hash": "56366ae30badd92b6fc0ef78b64b9db5c574b5fcd64c187738975107fa8889d2",
            "extract_dir": "Baulk-2.1.0-win-x86"
        }
    },
    "bin": "baulkterminal.exe",
    "checkver": "github",
    "autoupdate": {
        "architecture": {
            "64bit": {
                "url": "https://github.com/baulk/baulk/releases/download/$version/Baulk-$version-win-x64.zip",
                "extract_dir": "Baulk-$version-win-x64"
            },
            "32bit": {
                "url": "https://github.com/baulk/baulk/releases/download/$version/Baulk-$version-win-x86.zip",
                "extract_dir": "Baulk-$version-win-x86"
            }
        }
    }
}
