{
    "homepage": "https://live.bilibili.com/liveHime",
    "description": "BiliBili Live Streaming tool",
    "license": "Unknown",
    "version": "6.4.0.7482",
    "architecture": {
        "64bit": {
            "url": "https://dl.hdslb.com/bili/bililive/win/Livehime-Win-beta-6.4.0.7482-x64.exe",
            "hash": "md5:d9f044414c2adb7f5eca463a2d5e0eca"
        }
    },
    "depends": "innounp",
    "installer": {
        "script": "Expand-InnoArchive -Path \"$dir\\$fname\" -Removal"
    },
    "shortcuts": [
        [
            "livehime.exe",
            "Bilibili Live Hime"
        ]
    ],
    "checkver": {
        "url": "https://api.live.bilibili.com/xlive/app-blink/v1/liveVersionInfo/getHomePageLiveVersion?system_version=2",
        "jsonpath": "$.data.curr_version"
    },
    "autoupdate": {
        "architecture": {
            "64bit": {
                "url": "https://dl.hdslb.com/bili/bililive/win/Livehime-Win-beta-$version-x64.exe",
                "hash": {
                    "url": "https://api.live.bilibili.com/xlive/app-blink/v1/liveVersionInfo/getHomePageLiveVersion?system_version=2",
                    "jsonpath": "$.data.file_md5"
                }
            }
        }
    }
}
