{
    "homepage": "https://www.bypass.cn/",
    "description": "Bypass - Eaiser to buy your tickets",
    "version": "1.16.29",
    "license": "Freeware",
    "url": "https://www.bypass.cn/api/download?name=Bypass.zip#/dl.7z",
    "hash": "4a0343f6204f57bc43ebbac2f940d8984da6fce1817d06826f2a110c6a9aabbf",
    "extract_dir": "Bypass",
    "shortcuts": [
        [
            "Bypass.exe",
            "分流抢票"
        ]
    ],
    "checkver": {
        "regex": "Version.*?([\\d.]+)</label>"
    },
    "autoupdate": {
        "url": "https://www.bypass.cn/api/download?name=Bypass.zip#/dl.7z"
    },
    "notes": "Tips: the Bypass software requires elevated privileges to run."
}
