{
    "homepage": "https://duck.sh/",
    "description": "Cyberduck for the command line interface",
    "license": "GPL-2.0-or-later",
    "version": "8.8.1.41263",
    "url": "https://dist.duck.sh/duck-8.8.1.41263.msi",
    "hash": "8a94956c2060c3273dd112ef340b0e089f7f9f6ac8b2106c0747ceb53c58d0b3",
    "extract_dir": "Cyberduck CLI",
    "bin": "duck.exe",
    "checkver": {
        "url": "https://dist.duck.sh/",
        "re": "duck-([\\d.]+).msi"
    },
    "autoupdate": {
        "url": "https://dist.duck.sh/duck-$version.msi"
    },
    "notes": "Additional third party connection profiles can be installed to and found in '%APPDATA%\\Cyberduck\\Profiles'."
}
