{
    "homepage": "https://dz.blizzard.cn/",
    "description": "Warcraft III Battle Platform",
    "license": "Freeware",
    "version": "2.4.30",
    "url": "https://dz.gdl.netease.com/dzclient-2.4.30.exe#/dl.7z",
    "hash": "5fc8606eba0c92751919a229eeff75a29a2f34283ed003fa0787715a8d5e4d6c",
    "extract_dir": "$_3_",
    "post_install": "Remove-Item \"$dir\\`$_3_\" -Recurse",
    "shortcuts": [
        [
            "Platform.exe",
            "魔兽争霸官方对战平台"
        ]
    ],
    "checkver": {
        "url": "https://blz.nosdn.127.net/4/pf/ver/download.json",
        "regex": "dzclient-([\\d.]+).exe"
    },
    "autoupdate": {
        "url": "https://dz.gdl.netease.com/dzclient-$version.exe#/dl.7z"
    }
}
