{
    "homepage": "https://github.com/evanw/esbuild",
    "description": "An extremely fast JavaScript bundler and minifier",
    "version": "0.8.16",
    "license": "MIT",
    "architecture": {
        "64bit": {
            "url": "https://registry.yarnpkg.com/esbuild-windows-64/-/esbuild-windows-64-0.8.16.tgz",
            "hash": "sha1:6c51e4e90243c81cf9d5bec9b14271f3cc7f3edf"
        },
        "32bit": {
            "url": "https://registry.yarnpkg.com/esbuild-windows-32/-/esbuild-windows-32-0.8.16.tgz",
            "hash": "sha1:0bdbdd64ff9521ae6a987a58c2438ed394c13e22"
        }
    },
    "installer": {
        "script": [
            "Move-Item $dir\\package\\esbuild.exe $dir",
            "Remove-Item $dir\\package -Recurse -Force"
        ]
    },
    "bin": "esbuild.exe",
    "checkver": {
        "url": "https://registry.yarnpkg.com/esbuild-windows-64",
        "jsonpath": "$.dist-tags.latest"
    },
    "autoupdate": {
        "architecture": {
            "64bit": {
                "url": "https://registry.yarnpkg.com/esbuild-windows-64/-/esbuild-windows-64-$version.tgz",
                "hash": {
                    "url": "https://registry.yarnpkg.com/esbuild-windows-64",
                    "jsonpath": "$.versions.$version.dist.shasum"
                }
            },
            "32bit": {
                "url": "https://registry.yarnpkg.com/esbuild-windows-32/-/esbuild-windows-32-$version.tgz",
                "hash": {
                    "url": "https://registry.yarnpkg.com/esbuild-windows-32",
                    "jsonpath": "$.versions.$version.dist.shasum"
                }
            }
        }
    }
}
