{
    "version": "130.0b7",
    "description": "Beta builds of Firefox: the popular open source web browser.",
    "homepage": "https://www.mozilla.org/zh-CN/firefox/beta/",
    "license": "MPL-2.0",
    "architecture": {
        "64bit": {
            "url": "https://download-installer.cdn.mozilla.net/pub/firefox/releases/130.0b7/win64/zh-CN/Firefox%20Setup%20130.0b7.exe#/firefox-beta.7z",
            "hash": "sha512:1ce0bff66635662b207e48668c0ec9856ef5e2ad7bc4172c7ece6c62899c93e80883da6a747ec3814bc727e0bc586c160d69823272f9b4eb2f3f2d9400ac3437"
        },
        "32bit": {
            "url": "https://download-installer.cdn.mozilla.net/pub/firefox/releases/130.0b7/win32/zh-CN/Firefox%20Setup%20130.0b7.exe#/firefox-beta.7z",
            "hash": "sha512:7f6d6fca903f9e71156026c4433a82c12acbdca2119e5eeaa45112520e67c9c3b1d9af7a495b511cc482c798eedf2fbe04d1dfe9fdf891cdb28860cec2c712e4"
        }
    },
    "extract_dir": "core",
    "bin": [
        [
            "firefox.exe",
            "firefox-beta"
        ]
    ],
    "shortcuts": [
        [
            "firefox.exe",
            "Firefox Beta"
        ]
    ],
    "persist": "profile-portable",
    "checkver": {
        "url": "https://aus5.mozilla.org/update/6/Firefox/93.0/_/WINNT_x86_64-msvc-x64/en-US/beta/_/_/_/_/update.xml",
        "xpath": "/updates/update/patch/@URL",
        "regex": "firefox-([\\db.]+)-"
    },
    "autoupdate": {
        "architecture": {
            "64bit": {
                "url": "https://download-installer.cdn.mozilla.net/pub/firefox/releases/$version/win64/zh-CN/Firefox%20Setup%20$version.exe#/firefox-beta.7z",
                "hash": {
                    "url": "https://download-installer.cdn.mozilla.net/pub/firefox/releases/$version/SHA512SUMS",
                    "regex": "$sha512\\s+win64/zh-CN/$basename"
                }
            },
            "32bit": {
                "url": "https://download-installer.cdn.mozilla.net/pub/firefox/releases/$version/win32/zh-CN/Firefox%20Setup%20$version.exe#/firefox-beta.7z",
                "hash": {
                    "url": "https://download-installer.cdn.mozilla.net/pub/firefox/releases/$version/SHA512SUMS",
                    "regex": "$sha512\\s+win32/zh-CN/$basename"
                }
            }
        }
    },
    "notes": "To recover persisted profile, you need to open the Profile Manager with `firefox-beta -P` and create by selecting the portable profile directory."
}
