{
    "version": "153.0b2",
    "description": "Beta builds of Firefox: the popular open source web browser.",
    "homepage": "https://www.mozilla.org/zh-CN/firefox/beta/",
    "license": "MPL-2.0",
    "architecture": {
        "64bit": {
            "url": "https://download-installer.cdn.mozilla.net/pub/firefox/releases/153.0b2/win64/zh-CN/Firefox%20Setup%20153.0b2.exe#/firefox-beta.7z",
            "hash": "sha512:4c87057c42c640882b95f5776444c972847f401958e8ed8be01834a0fe1304f433bb4327211a3f2a95234bf2791a98dd064e3cbb1a39f78a2ccbec46f3c5e751"
        },
        "32bit": {
            "url": "https://download-installer.cdn.mozilla.net/pub/firefox/releases/153.0b2/win32/zh-CN/Firefox%20Setup%20153.0b2.exe#/firefox-beta.7z",
            "hash": "sha512:bb7c0d26d6f9c4bbd18b5770872f516a12c9f7374e281ebc4084806f48a59ecc88b11fa5465bf77b7fc44cabdce030ae8d970f5d9471ef1043a794a36619ba35"
        }
    },
    "extract_dir": "core",
    "bin": [
        [
            "firefox.exe",
            "firefox-beta"
        ]
    ],
    "shortcuts": [
        [
            "firefox.exe",
            "Firefox Beta"
        ]
    ],
    "persist": "profile-portable",
    "checkver": {
        "url": "https://aus5.mozilla.org/update/6/Firefox/93.0/_/WINNT_x86_64-msvc-x64/en-US/beta/_/_/_/_/update.xml",
        "xpath": "/updates/update/patch/@URL",
        "regex": "firefox-([\\db.]+)-"
    },
    "autoupdate": {
        "architecture": {
            "64bit": {
                "url": "https://download-installer.cdn.mozilla.net/pub/firefox/releases/$version/win64/zh-CN/Firefox%20Setup%20$version.exe#/firefox-beta.7z",
                "hash": {
                    "url": "https://download-installer.cdn.mozilla.net/pub/firefox/releases/$version/SHA512SUMS",
                    "regex": "$sha512\\s+win64/zh-CN/$basename"
                }
            },
            "32bit": {
                "url": "https://download-installer.cdn.mozilla.net/pub/firefox/releases/$version/win32/zh-CN/Firefox%20Setup%20$version.exe#/firefox-beta.7z",
                "hash": {
                    "url": "https://download-installer.cdn.mozilla.net/pub/firefox/releases/$version/SHA512SUMS",
                    "regex": "$sha512\\s+win32/zh-CN/$basename"
                }
            }
        }
    },
    "notes": "To recover persisted profile, you need to open the Profile Manager with `firefox-beta -P` and create by selecting the portable profile directory."
}
