{
    "homepage": "https://itch.io/app",
    "description": "The itch.io desktop app",
    "version": "25.6.2",
    "license": "MIT",
    "architecture": {
        "64bit": {
            "url": "https://broth.itch.ovh/itch/windows-amd64/25.6.2/archive/default#/dl.7z",
            "hash": "86c05d4d05f90b18fef3a302c8fcabd5e5a42cb699c1747c89080c44db7485bc"
        },
        "32bit": {
            "url": "https://broth.itch.ovh/itch/windows-386/25.6.2/archive/default#/dl.7z",
            "hash": "fb79a8fb9329b663d68aff7901916fd6bf5532eb9d3070154f3afcbf049a7e60"
        }
    },
    "bin": "itch.exe",
    "shortcuts": [
        [
            "itch.exe",
            "itch"
        ]
    ],
    "checkver": {
        "url": "https://itchio.itch.io/itch",
        "regex": "(?sm)itch-windows-amd64.zip.*Version ([\\d.]+)"
    },
    "autoupdate": {
        "architecture": {
            "64bit": {
                "url": "https://broth.itch.ovh/itch/windows-amd64/$version/archive/default#/dl.7z"
            },
            "32bit": {
                "url": "https://broth.itch.ovh/itch/windows-386/$version/archive/default#/dl.7z"
            }
        }
    }
}
