{
    "homepage": "https://lv.ulikecam.com/",
    "description": "Video editing application produced by ByteDance",
    "license": "Proprietary",
    "version": "2.1.1.4602",
    "url": "https://lf3-faceucdn-tos.pstatp.com/obj/faceu-packages/Jianying_pro_2_1_1_4602_jianyingpro_0.exe#/jianyingpro.7z",
    "hash": "96940f9b31e038c19fd9739db9d54832be43c53a778915e952f15efc43ed27e9",
    "extract_dir": "JYPacket",
    "shortcuts": [
        [
            "JianyingPro.exe",
            "剪映专业版"
        ]
    ],
    "checkver": {
        "url": "https://sf1-hscdn-tos.pstatp.com/obj/ies-fe-bee/bee_prod/biz_80/bee_prod_80_bee_publish_3563.json",
        "regex": "/Jianying_pro_(?<major>[\\d]+)_(?<minor>[\\d]+)_(?<patch>[\\d]+)_(?<build>[\\d]+)_jianyingpro_0.exe",
        "replace": "${major}.${minor}.${patch}.${build}"
    },
    "autoupdate": {
        "url": "https://lf3-faceucdn-tos.pstatp.com/obj/faceu-packages/Jianying_pro_$underscoreVersion_jianyingpro_0.exe#/jianyingpro.7z"
    }
}
