{
    "version": "22.12.3-1295",
    "description": "Enabling communication between all your devices. Made for people like you.",
    "homepage": "https://kdeconnect.kde.org",
    "license": "GPL-2.0-or-later",
    "url": "https://binary-factory.kde.org/job/kdeconnect-kde_Release_win64/1295/artifact/kdeconnect-kde-22.12.3-1295-windows-cl-msvc2019-x86_64.7z",
    "hash": "8230f55414c28cf65693e7bb98ba260e04eeb5b8d74f0dfac43a75e725a7894a",
    "bin": "bin\\kdeconnect-cli.exe",
    "shortcuts": [
        [
            "bin\\kdeconnect-indicator.exe",
            "KDE Connect"
        ]
    ],
    "checkver": {
        "url": "https://binary-factory.kde.org/job/kdeconnect-kde_Release_win64/lastSuccessfulBuild/api/json/",
        "regex": "kdeconnect-kde-([\\d.]+-(?<build>\\d+)).*"
    },
    "autoupdate": {
        "url": "https://binary-factory.kde.org/job/kdeconnect-kde_Release_win64/$matchBuild/artifact/kdeconnect-kde-$version-windows-cl-msvc2019-x86_64.7z",
        "hash": {
            "url": "$url.sha256",
            "regex": "$sha256"
        }
    },
    "notes": "Scoop doesn't persist your KDE Connect data, they are still storaged in '%LOCALAPPDATA%\\kdeconnect'."
}
