{
    "homepage": "https://www.microsoft.com/en-us/edge",
    "description": "The chromium based Microsoft Edge browser (Canary Channel)",
    "version": "113.0.1753.0",
    "license": "Freeware",
    "architecture": {
        "64bit": {
            "url": "https://dorado-api.deno.dev/edge?arch=64&channel=canary&version=113.0.1753.0&dl#/MicrosoftEdge-113.0.1753.0-x64.7z",
            "hash": "0c3cf109d7b6c520d3a8eecad4265ae19bdd174b923ead7bb5665ef274866c5d"
        },
        "32bit": {
            "url": "https://dorado-api.deno.dev/edge?arch=86&channel=canary&version=113.0.1753.0&dl#/MicrosoftEdge-113.0.1753.0-x86.7z",
            "hash": "2388e04bffd9f80621f856efce94ba653d9cfea2d1e859d6a5196da78705dac9"
        }
    },
    "installer": {
        "script": "Expand-7zipArchive -Path \"$dir\\MSEDGE.7z\" -ExtractDir \"Chrome-bin\\$version\" -Removal"
    },
    "shortcuts": [
        [
            "msedge.exe",
            "Microsoft Edge Canary"
        ]
    ],
    "checkver": {
        "url": "https://dorado-api.deno.dev/edge?arch=64&channel=canary",
        "jsonpath": "$.Version"
    },
    "autoupdate": {
        "architecture": {
            "64bit": {
                "url": "https://dorado-api.deno.dev/edge?arch=64&channel=canary&version=$version&dl#/MicrosoftEdge-$version-x64.7z",
                "hash": {
                    "url": "https://dorado-api.deno.dev/edge?arch=64&channel=canary&version=$version",
                    "jsonpath": "$.Hashes.Sha256"
                }
            },
            "32bit": {
                "url": "https://dorado-api.deno.dev/edge?arch=86&channel=canary&version=$version&dl#/MicrosoftEdge-$version-x86.7z",
                "hash": {
                    "url": "https://dorado-api.deno.dev/edge?arch=86&channel=canary&version=$version",
                    "jsonpath": "$.Hashes.Sha256"
                }
            }
        }
    }
}
