{
    "homepage": "https://www.microsoft.com/en-us/edge",
    "description": "The chromium based Microsoft Edge browser (Canary Channel)",
    "version": "93.0.967.0",
    "license": "Freeware",
    "architecture": {
        "64bit": {
            "url": "https://dorado-api.deno.dev/edge?arch=64&channel=canary&dl#/MicrosoftEdge-93.0.967.0-x64.7z",
            "hash": "95c9ff0ac1fa9029dd77a4c9a97dd053352c1f1471803703f238e3419f23280d"
        },
        "32bit": {
            "url": "https://dorado-api.deno.dev/edge?arch=86&channel=canary&dl#/MicrosoftEdge-93.0.967.0-x86.7z",
            "hash": "e87fd5a0bd1b32351b9759801fb083c9223ea58200d395b909cefdf6ec4852fa"
        }
    },
    "installer": {
        "script": "Expand-7zipArchive -Path \"$dir\\MSEDGE.7z\" -ExtractDir \"Chrome-bin\\$version\" -Removal"
    },
    "shortcuts": [
        [
            "msedge.exe",
            "Microsoft Edge Canary"
        ]
    ],
    "checkver": {
        "url": "https://edgeupdates.microsoft.com/api/products",
        "jsonpath": "$[?(@.Product == 'Canary')].Releases[?(@.Platform == 'Windows' && @.Architecture == 'x64')].ProductVersion"
    },
    "autoupdate": {
        "architecture": {
            "64bit": {
                "url": "https://dorado-api.deno.dev/edge?arch=64&channel=canary&dl#/MicrosoftEdge-$version-x64.7z",
                "hash": {
                    "url": "https://dorado-api.deno.dev/edge?arch=64&channel=canary",
                    "jsonpath": "$.Hashes.Sha256"
                }
            },
            "32bit": {
                "url": "https://dorado-api.deno.dev/edge?arch=86&channel=canary&dl#/MicrosoftEdge-$version-x86.7z",
                "hash": {
                    "url": "https://dorado-api.deno.dev/edge?arch=86&channel=canary",
                    "jsonpath": "$.Hashes.Sha256"
                }
            }
        }
    }
}
