{
    "homepage": "https://www.microsoft.com/en-us/edge",
    "description": "The chromium based Microsoft Edge browser (Canary Channel)",
    "version": "126.0.2544.0",
    "license": "Freeware",
    "architecture": {
        "64bit": {
            "url": "https://dorado-api.deno.dev/edge?arch=64&channel=canary&version=126.0.2544.0&dl#/MicrosoftEdge-126.0.2544.0-x64.7z",
            "hash": "ebfc2a54971a98b376bc37128dc745996f768df4b450ce612a14ff0aac92437a"
        },
        "32bit": {
            "url": "https://dorado-api.deno.dev/edge?arch=86&channel=canary&version=126.0.2544.0&dl#/MicrosoftEdge-126.0.2544.0-x86.7z",
            "hash": "24c305ca50b649c3494d8d276990d5b74798b7e84b19e33177bafe680c96ef4f"
        },
        "arm64": {
            "url": "https://dorado-api.deno.dev/edge?arch=arm64&channel=canary&version=126.0.2544.0&dl#/MicrosoftEdge-126.0.2544.0-arm64.7z",
            "hash": "1db7ac5caeb089f38025a4e431001d1d2b9376688127a859360feb6b10782742"
        }
    },
    "installer": {
        "script": "Expand-7zipArchive -Path \"$dir\\MSEDGE.7z\" -ExtractDir \"Chrome-bin\\$version\" -Removal"
    },
    "shortcuts": [
        [
            "msedge.exe",
            "Microsoft Edge Canary"
        ]
    ],
    "checkver": {
        "url": "https://dorado-api.deno.dev/edge?arch=64&channel=canary",
        "jsonpath": "$.Version"
    },
    "autoupdate": {
        "architecture": {
            "64bit": {
                "url": "https://dorado-api.deno.dev/edge?arch=64&channel=canary&version=$version&dl#/MicrosoftEdge-$version-x64.7z",
                "hash": {
                    "url": "https://dorado-api.deno.dev/edge?arch=64&channel=canary&version=$version",
                    "jsonpath": "$.Hashes.Sha256"
                }
            },
            "32bit": {
                "url": "https://dorado-api.deno.dev/edge?arch=86&channel=canary&version=$version&dl#/MicrosoftEdge-$version-x86.7z",
                "hash": {
                    "url": "https://dorado-api.deno.dev/edge?arch=86&channel=canary&version=$version",
                    "jsonpath": "$.Hashes.Sha256"
                }
            },
            "arm64": {
                "url": "https://dorado-api.deno.dev/edge?arch=arm64&channel=canary&version=$version&dl#/MicrosoftEdge-$version-arm64.7z",
                "hash": {
                    "url": "https://dorado-api.deno.dev/edge?arch=arm64&channel=canary&version=$version",
                    "jsonpath": "$.Hashes.Sha256"
                }
            }
        }
    }
}
