{
    "homepage": "https://www.microsoft.com/en-us/edge",
    "description": "The chromium based Microsoft Edge browser (Canary Channel)",
    "version": "131.0.2890.0",
    "license": "Freeware",
    "architecture": {
        "64bit": {
            "url": "https://dorado-api.deno.dev/edge?arch=64&channel=canary&version=131.0.2890.0&dl#/MicrosoftEdge-131.0.2890.0-x64.7z",
            "hash": "aa1fd0f592455d5ad2195218d4ea27e13ed77c8008c30a88e69b9591692d424c"
        },
        "32bit": {
            "url": "https://dorado-api.deno.dev/edge?arch=86&channel=canary&version=131.0.2890.0&dl#/MicrosoftEdge-131.0.2890.0-x86.7z",
            "hash": "05fa65565d5edb2d8c1cfeac0bca809fea594130bb4f9dc33719c79024b60140"
        },
        "arm64": {
            "url": "https://dorado-api.deno.dev/edge?arch=arm64&channel=canary&version=131.0.2890.0&dl#/MicrosoftEdge-131.0.2890.0-arm64.7z",
            "hash": "e770847c01f17f1975dd08d8d5c6ad443b9de4c2cd25d879cd7a35af2a4f16ad"
        }
    },
    "installer": {
        "script": "Expand-7zipArchive -Path \"$dir\\MSEDGE.7z\" -ExtractDir \"Chrome-bin\\$version\" -Removal"
    },
    "shortcuts": [
        [
            "msedge.exe",
            "Microsoft Edge Canary"
        ]
    ],
    "checkver": {
        "url": "https://dorado-api.deno.dev/edge?arch=64&channel=canary",
        "jsonpath": "$.Version"
    },
    "autoupdate": {
        "architecture": {
            "64bit": {
                "url": "https://dorado-api.deno.dev/edge?arch=64&channel=canary&version=$version&dl#/MicrosoftEdge-$version-x64.7z",
                "hash": {
                    "url": "https://dorado-api.deno.dev/edge?arch=64&channel=canary&version=$version",
                    "jsonpath": "$.Hashes.Sha256"
                }
            },
            "32bit": {
                "url": "https://dorado-api.deno.dev/edge?arch=86&channel=canary&version=$version&dl#/MicrosoftEdge-$version-x86.7z",
                "hash": {
                    "url": "https://dorado-api.deno.dev/edge?arch=86&channel=canary&version=$version",
                    "jsonpath": "$.Hashes.Sha256"
                }
            },
            "arm64": {
                "url": "https://dorado-api.deno.dev/edge?arch=arm64&channel=canary&version=$version&dl#/MicrosoftEdge-$version-arm64.7z",
                "hash": {
                    "url": "https://dorado-api.deno.dev/edge?arch=arm64&channel=canary&version=$version",
                    "jsonpath": "$.Hashes.Sha256"
                }
            }
        }
    }
}
