{
    "homepage": "https://www.microsoft.com/en-us/edge",
    "description": "The chromium based Microsoft Edge browser (Canary Channel)",
    "version": "123.0.2405.0",
    "license": "Freeware",
    "architecture": {
        "64bit": {
            "url": "https://dorado-api.deno.dev/edge?arch=64&channel=canary&version=123.0.2405.0&dl#/MicrosoftEdge-123.0.2405.0-x64.7z",
            "hash": "2bf373175570af6b506a4a22ea64159822d8ec3b8b7145f6646d92e0a6b1b7e4"
        },
        "32bit": {
            "url": "https://dorado-api.deno.dev/edge?arch=86&channel=canary&version=123.0.2405.0&dl#/MicrosoftEdge-123.0.2405.0-x86.7z",
            "hash": "b955a9fd69a50313939ce7aeebdeb249aa2bbce17d517425d633389eea87bcf5"
        },
        "arm64": {
            "url": "https://dorado-api.deno.dev/edge?arch=arm64&channel=canary&version=123.0.2405.0&dl#/MicrosoftEdge-123.0.2405.0-arm64.7z",
            "hash": "48d2d1e12f338124313b33a8db74e27e47c7929679ac97817bb52adcd7f5a004"
        }
    },
    "installer": {
        "script": "Expand-7zipArchive -Path \"$dir\\MSEDGE.7z\" -ExtractDir \"Chrome-bin\\$version\" -Removal"
    },
    "shortcuts": [
        [
            "msedge.exe",
            "Microsoft Edge Canary"
        ]
    ],
    "checkver": {
        "url": "https://dorado-api.deno.dev/edge?arch=64&channel=canary",
        "jsonpath": "$.Version"
    },
    "autoupdate": {
        "architecture": {
            "64bit": {
                "url": "https://dorado-api.deno.dev/edge?arch=64&channel=canary&version=$version&dl#/MicrosoftEdge-$version-x64.7z",
                "hash": {
                    "url": "https://dorado-api.deno.dev/edge?arch=64&channel=canary&version=$version",
                    "jsonpath": "$.Hashes.Sha256"
                }
            },
            "32bit": {
                "url": "https://dorado-api.deno.dev/edge?arch=86&channel=canary&version=$version&dl#/MicrosoftEdge-$version-x86.7z",
                "hash": {
                    "url": "https://dorado-api.deno.dev/edge?arch=86&channel=canary&version=$version",
                    "jsonpath": "$.Hashes.Sha256"
                }
            },
            "arm64": {
                "url": "https://dorado-api.deno.dev/edge?arch=arm64&channel=canary&version=$version&dl#/MicrosoftEdge-$version-arm64.7z",
                "hash": {
                    "url": "https://dorado-api.deno.dev/edge?arch=arm64&channel=canary&version=$version",
                    "jsonpath": "$.Hashes.Sha256"
                }
            }
        }
    }
}
