{
    "homepage": "https://github.com/moonlight-stream/moonlight-qt",
    "description": "GameStream client for PCs (Windows, Mac, Linux, and Steam Link)",
    "version": "6.0.0",
    "license": "GPL-3.0-only",
    "architecture": {
        "32bit": {
            "url": "https://github.com/moonlight-stream/moonlight-qt/releases/download/v6.0.0/MoonlightPortable-x86-6.0.0.zip",
            "hash": "cd0cbe8979f7f0a699d395fdcf34efd359f4d379ae24b9901a3f452e043f6578"
        },
        "64bit": {
            "url": "https://github.com/moonlight-stream/moonlight-qt/releases/download/v6.0.0/MoonlightPortable-x64-6.0.0.zip",
            "hash": "b32a6f334e54fbd09672819c16a7738c95e0390b80cd771bbd0483a006e81628"
        }
    },
    "persist": "Moonlight Game Streaming Project",
    "shortcuts": [
        [
            "Moonlight.exe",
            "Moonlight"
        ]
    ],
    "checkver": "github",
    "autoupdate": {
        "architecture": {
            "32bit": {
                "url": "https://github.com/moonlight-stream/moonlight-qt/releases/download/v$version/MoonlightPortable-x86-$version.zip"
            },
            "64bit": {
                "url": "https://github.com/moonlight-stream/moonlight-qt/releases/download/v$version/MoonlightPortable-x64-$version.zip"
            }
        }
    }
}
