{
    "homepage": "https://uu.163.com/",
    "description": "Game accelerator created by Netease Inc.",
    "version": "4.14.1.4026",
    "license": {
        "identifier": "EULA",
        "url": "https://uu.163.com/agreement.html"
    },
    "url": "https://uu.gdl.netease.com/4026/UU-4.14.1.exe#/dl.7z",
    "hash": "00d661d339d752591ce13b8e61c55d7650bf6c28bde9c976f4461673d6f31f18",
    "shortcuts": [
        [
            "uu.exe",
            "网易UU"
        ]
    ],
    "checkver": {
        "url": "https://uu.163.com/baike/js/dl.js",
        "regex": "'dlUrl': 'https://.*?.gdl.netease.com/(?<build>\\d+)/UU-(?<ver>[\\d.]+).exe'",
        "replace": "${ver}.${build}"
    },
    "autoupdate": {
        "url": "https://uu.gdl.netease.com/$matchBuild/UU-$matchVer.exe#/dl.7z"
    }
}
