{
    "homepage": "https://github.com/YerongAI/Office-Tool",
    "description": "Office Tool Plus is a tool for managing, downloading and installing Office.",
    "version": "7.6.0.1",
    "license": "GPL-3.0-only",
    "url": "https://github.com/YerongAI/Office-Tool/releases/download/7.6.0.1/Office-Tool-v7.6.zip",
    "hash": "aab3a5d71be3489d4c86ccf03f2d29f94d4192843cbb95816bd65de85236bc51",
    "extract_dir": "Office Tool",
    "shortcuts": [
        [
            "Office Tool Plus.exe",
            "Office Tool Plus"
        ]
    ],
    "persist": "Office",
    "checkver": "github",
    "autoupdate": {
        "url": "https://github.com/YerongAI/Office-Tool/releases/download/$version/Office-Tool-v$majorVersion.$minorVersion.zip"
    }
}
