{
    "homepage": "https://github.com/PowerShell/PowerShell",
    "description": "PowerShell Core, the cross-platform task automation and configuration management framework/tool.",
    "version": "7.2.7",
    "license": "MIT",
    "architecture": {
        "64bit": {
            "url": "https://github.com/PowerShell/PowerShell/releases/download/v7.2.7/PowerShell-7.2.7-win-x64.zip",
            "hash": "4686202e22ec153f4fef0b4d7fb2d577a6b0cd4d448b598e151417d095bc8fad"
        },
        "32bit": {
            "url": "https://github.com/PowerShell/PowerShell/releases/download/v7.2.7/PowerShell-7.2.7-win-x86.zip",
            "hash": "c82c042e05ba7fc66dd84d43fa46b33131acfc7028b8af724ac149171d2d24b5"
        }
    },
    "bin": "pwsh.exe",
    "shortcuts": [
        [
            "pwsh.exe",
            "PowerShell"
        ]
    ],
    "checkver": {
        "url": "https://raw.githubusercontent.com/PowerShell/PowerShell/master/README.md",
        "regex": "\\[rl-windows-64\\].*releases/download/v([\\d.]+)/PowerShell"
    },
    "autoupdate": {
        "architecture": {
            "64bit": {
                "url": "https://github.com/PowerShell/PowerShell/releases/download/v$version/PowerShell-$version-win-x64.zip"
            },
            "32bit": {
                "url": "https://github.com/PowerShell/PowerShell/releases/download/v$version/PowerShell-$version-win-x86.zip"
            }
        },
        "hash": {
            "url": "https://github.com/PowerShell/PowerShell/releases/tag/v$version/",
            "find": "$basename\\s*<ul>\\s*<li>([A-Fa-f\\d]{64})"
        }
    }
}
