{
    "version": "24.3.2",
    "description": "Trezor Suite application (Trezor Desktop)",
    "homepage": "https://trezor.io/trezor-suite",
    "license": {
        "identifier": "Proprietary",
        "url": "https://github.com/trezor/trezor-suite/blob/develop/LICENSE.md"
    },
    "architecture": {
        "64bit": {
            "url": "https://github.com/trezor/trezor-suite/releases/download/v24.3.2/Trezor-Suite-24.3.2-win-x64.exe#/dl.7z",
            "hash": "sha512:7ca66e4666dd6b93e6e31eb7d0282638be04c933733b157740f165c0d20e457e664717348c517b3b14b6b04fcc7d4b80d74f356e78dca11e8b3ea0d552c9eb96",
            "installer": {
                "script": [
                    "Expand-7zipArchive \"$dir\\`$PLUGINSDIR\\app-64.7z\" -DestinationPath \"$dir\" -Removal",
                    "Remove-Item \"$dir\\`$PLUGINSDIR\",\"$dir\\`$R0\" -Force -Recurse"
                ]
            }
        }
    },
    "shortcuts": [
        [
            "Trezor Suite.exe",
            "Trezor Suite"
        ]
    ],
    "checkver": {
        "github": "https://github.com/trezor/trezor-suite"
    },
    "autoupdate": {
        "architecture": {
            "64bit": {
                "url": "https://github.com/trezor/trezor-suite/releases/download/v$version/Trezor-Suite-$version-win-x64.exe#/dl.7z"
            }
        },
        "hash": {
            "url": "https://github.com/trezor/trezor-suite/releases/download/v$version/latest.yml",
            "mode": "extract",
            "regex": "(?sm)$version-win-x64.exe.*?sha512: $base64"
        }
    }
}
