{
    "version": "1.229.0",
    "description": "CLI and Rust libraries for low-level manipulation of WebAssembly modules",
    "homepage": "https://github.com/bytecodealliance/wasm-tools",
    "license": "Apache-2.0|MIT",
    "architecture": {
        "64bit": {
            "url": "https://github.com/bytecodealliance/wasm-tools/releases/download/v1.229.0/wasm-tools-1.229.0-x86_64-windows.zip",
            "hash": "26a69942982cbc533e5704b654f303ac681ce8f1dd9265d082816915528dee02",
            "extract_dir": "wasm-tools-1.229.0-x86_64-windows"
        }
    },
    "bin": "wasm-tools.exe",
    "checkver": "github",
    "autoupdate": {
        "architecture": {
            "64bit": {
                "url": "https://github.com/bytecodealliance/wasm-tools/releases/download/v$version/wasm-tools-$version-x86_64-windows.zip",
                "extract_dir": "wasm-tools-$version-x86_64-windows"
            }
        }
    }
}
