{
    "version": "5.1.0",
    "homepage": "https://www.anaconda.com/",
    "license": "BSD 3-Clause",
    "checkver": {
        "url": "https://repo.continuum.io/archive",
        "re": "Anaconda3-([\\d.]+)-Windows"
    },
    "architecture": {
        "64bit": {
            "url": "https://repo.continuum.io/archive/Anaconda3-5.1.0-Windows-x86_64.exe",
            "hash": "md5:83a8b1edcb21fa0ac481b23f65b604c6"
        },
        "32bit": {
            "url": "https://repo.continuum.io/archive/Anaconda3-5.1.0-Windows-x86.exe",
            "hash": "md5:7a2291ab99178a4cdec530861494531f"
        }
    },
    "autoupdate": {
        "architecture": {
            "64bit": {
                "url": "https://repo.continuum.io/archive/Anaconda3-$version-Windows-x86_64.exe"
            },
            "32bit": {
                "url": "https://repo.continuum.io/archive/Anaconda3-$version-Windows-x86.exe"
            }
        },
        "hash": {
            "url": "$baseurl",
            "find": "$basename<.*\\s+<.*\\s+<.*\\s+<td>([a-fA-F0-9]{32})</td>"
        }
    },
    "installer": {
        "args": [
            "/S",
            "/InstallationType=JustMe",
            "/RegisterPython=0",
            "/AddToPath=0",
            "/D=$dir"
        ]
    },
    "uninstaller": {
        "file": "Uninstall-Anaconda3.exe",
        "args": [
            "/S"
        ]
    },
    "bin": [
        "python.exe",
        "pythonw.exe",
        [
            "python.exe",
            "python3"
        ]
    ],
    "persist": [
        "envs"
    ],
    "env_add_path": "scripts",
    "notes": [
        "Currently conda envs activate and deactivate doesn't work on PowerShell,
        for more information, see: https://github.com/conda/conda/issues/626,
        or just execute: 'conda install -n root -c pscondaenvs pscondaenvs'"
    ]
}
